[{"closed":false,"segs":[{"color":"#ffffff","points":[{"a":116.6,"d":8.94},{"a":123.7,"d":7.21},{"a":56.3,"d":7.21},{"a":63.4,"d":8.94},{"a":69.4,"d":8.54},{"a":66.8,"d":7.62},{"a":113.2,"d":7.62},{"a":110.6,"d":8.54}]}]},{"closed":false,"segs":[{"color":"#ffffff","points":[{"a":121.6,"d":7.63},{"a":137.1,"d":9.55},{"a":270,"d":7.5},{"a":42.9,"d":9.55},{"a":58.4,"d":7.63}]}]},{"closed":false,"segs":[{"color":"#ffffff","points":[{"a":270,"d":5.5},{"a":132.7,"d":8.85},{"a":270,"d":5.5},{"a":47.3,"d":8.85}]}]},{"closed":false,"segs":[{"color":"#ffffff","points":[{"a":32.5,"d":6.52},{"a":59.7,"d":6.95},{"a":120.3,"d":6.95},{"a":147.5,"d":6.52}]}]},{"closed":false,"segs":[{"color":"#ffffff","points":[{"a":172.9,"d":4.03},{"a":104,"d":6.18},{"a":76,"d":6.18},{"a":7.1,"d":4.03}]}]},{"closed":false,"segs":[{"color":"#ffffff","points":[{"a":-60.3,"d":4.03},{"a":85.2,"d":6.02},{"a":94.8,"d":6.02},{"a":240.3,"d":4.03}]}]},{"closed":false,"segs":[{"color":"#ffffff","points":[{"a":270,"d":7},{"a":90,"d":6}]}]},{"closed":false,"segs":[{"color":"#ffffff","points":[{"a":110.6,"d":8.54},{"a":116.6,"d":8.94}]}]},{"closed":false,"segs":[{"color":"#ffffff","points":[{"a":110.6,"d":8.54},{"a":69.4,"d":8.54}]}]},{"closed":false,"segs":[{"color":"#ffffff","points":[{"a":110.6,"d":8.54},{"a":116.6,"d":8.94},{"a":119.7,"d":8.06}]}]},{"closed":false,"segs":[{"color":"#ffffff","points":[{"a":270,"d":7.5},{"a":270,"d":6.5}]}]}]